convexus/__init__.py
convexus/icontoolkit/BigInt.py
convexus/icontoolkit/__init__.py
convexus/icontoolkit/asynchronous.py
convexus/icontoolkit/calldata.py
convexus/icontoolkit/constants.py
convexus/icontoolkit/contract.py
convexus/icontoolkit/expect.py
convexus/icontoolkit/interface.py
convexus/icontoolkit/pack.py
convexus/icontoolkit/validateAndParseAddress.py
convexus/sdk/__init__.py
convexus/sdk/constants.py
convexus/sdk/internalConstants.py
convexus/sdk/nonfungiblePositionManager.py
convexus/sdk/payments.py
convexus/sdk/poolInitializer.py
convexus/sdk/quoter.py
convexus/sdk/staker.py
convexus/sdk/swapRouter.py
convexus/sdk/artifacts/__init__.py
convexus/sdk/artifacts/contracts/ConvexusPool.py
convexus/sdk/artifacts/contracts/ConvexusStaker.py
convexus/sdk/artifacts/contracts/IRC2.py
convexus/sdk/artifacts/contracts/NonfungiblePositionManager.py
convexus/sdk/artifacts/contracts/PoolInitializer.py
convexus/sdk/artifacts/contracts/Quoter.py
convexus/sdk/artifacts/contracts/SwapRouter.py
convexus/sdk/artifacts/contracts/__init__.py
convexus/sdk/entities/__init__.py
convexus/sdk/entities/eventlogs.py
convexus/sdk/entities/factoryProvider.py
convexus/sdk/entities/observation.py
convexus/sdk/entities/pool.py
convexus/sdk/entities/position.py
convexus/sdk/entities/results.py
convexus/sdk/entities/route.py
convexus/sdk/entities/slot0.py
convexus/sdk/entities/tick.py
convexus/sdk/entities/tickDataProvider.py
convexus/sdk/entities/tickListDataProvider.py
convexus/sdk/entities/trade.py
convexus/sdk/utils/__init__.py
convexus/sdk/utils/decodeSqrtRatioX96.py
convexus/sdk/utils/encodeRouteToPath.py
convexus/sdk/utils/encodeSqrtRatioX96.py
convexus/sdk/utils/fullMath.py
convexus/sdk/utils/isSorted.py
convexus/sdk/utils/liquidityMath.py
convexus/sdk/utils/maxLiquidityForAmounts.py
convexus/sdk/utils/mostSignificantBit.py
convexus/sdk/utils/nearestUsableTick.py
convexus/sdk/utils/position.py
convexus/sdk/utils/priceTickConversions.py
convexus/sdk/utils/sqrtPriceMath.py
convexus-1.1.20.dist-info/LICENSE
convexus-1.1.20.dist-info/METADATA
convexus-1.1.20.dist-info/WHEEL
convexus-1.1.20.dist-info/top_level.txt
convexus-1.1.20.dist-info/RECORD
