Metadata-Version: 2.1
Name: convexus
Version: 1.1.20
Summary: Convexus SDK for Python is useful for building applications on top of Convexus
Home-page: https://github.com/Convexus-Protocol/convexus-sdk-py
Author: Convexus
Author-email: convexus.protocol@gmail.com
License: Apache License 2.0
Classifier: Development Status :: 5 - Production/Stable
Classifier: Intended Audience :: Developers
Classifier: Intended Audience :: System Administrators
Classifier: Natural Language :: English
Classifier: License :: OSI Approved :: Apache Software License
Classifier: Programming Language :: Python :: 3.10
Requires-Python: ~=3.10
License-File: LICENSE
Requires-Dist: iconsdk (>=2.1.0)
Provides-Extra: tests
Requires-Dist: pytest (~=7.1.3) ; extra == 'tests'
